pyevspace.cp310-win_amd64.pyd
pyevspace-0.0.3.dist-info/LICENSE.txt
pyevspace-0.0.3.dist-info/METADATA
pyevspace-0.0.3.dist-info/WHEEL
pyevspace-0.0.3.dist-info/top_level.txt
pyevspace-0.0.3.dist-info/RECORD
