Metadata-Version: 2.1
Name: pyevspace
Version: 0.0.3
Summary: A Euclidean vector space module.
Home-page: https://github.com/qbizzle68/pyevspace
Author: Quinton Barnes
Author-email: devqbizzle68@gmail.com
License: MIT
Classifier: License :: OSI Approved :: MIT License
Classifier: Programming Language :: Python :: 3
Classifier: Programming Language :: Python :: Implementation :: CPython
Requires-Python: >=3.6
License-File: LICENSE.txt
